<?xml version="1.0" encoding="UTF-8" standalone="no"?><appliance-list><oven><power-consumption>2000</power-consumption><weight>11</weight><capacity>33</capacity><depth>60</depth><height>40.0</height><width>70.0</width></oven><oven><power-consumption>1500</power-consumption><weight>12</weight><capacity>33</capacity><depth>60</depth><height>45.0</height><width>68.0</width></oven><tablet-pc><battery-capacity>3</battery-capacity><display-inches>14</display-inches><memory-rom>8000</memory-rom><flash-memory-capacity>2</flash-memory-capacity><color>blue</color></tablet-pc></appliance-list>